math_pip/__init__.py
math_pip/math_operations.py
math_pip/version.py
math_pip-0.0.1.dist-info/licenses/LICENSE
math_pip-0.0.1.dist-info/METADATA
math_pip-0.0.1.dist-info/WHEEL
math_pip-0.0.1.dist-info/top_level.txt
math_pip-0.0.1.dist-info/RECORD
